jmeter_metrics_visualizer/__init__.py
jmeter_metrics_visualizer/generate_report.py
jmeter_metrics_visualizer/template/template.html
jmeter_metrics_visualizer-0.5.0.dist-info/METADATA
jmeter_metrics_visualizer-0.5.0.dist-info/WHEEL
jmeter_metrics_visualizer-0.5.0.dist-info/top_level.txt
jmeter_metrics_visualizer-0.5.0.dist-info/RECORD
